setup.cfg
setup.py
ORobin/__init__.py
ORobin.egg-info/PKG-INFO
ORobin.egg-info/SOURCES.txt
ORobin.egg-info/dependency_links.txt
ORobin.egg-info/not-zip-safe
ORobin.egg-info/top_level.txt