Metadata-Version: 1.0
Name: ORobin
Version: 0.5.40
Summary: It is programming language in russian! Main project - robin_pl!
Home-page: UNKNOWN
Author: FotonPC
Author-email: foton-pc@inbox.ru
License: UNKNOWN
Platform: UNKNOWN
